xxpaper/LiberationSans-Bold.ttf
xxpaper/LiberationSans-BoldItalic.ttf
xxpaper/LiberationSans-Italic.ttf
xxpaper/LiberationSans-Regular.ttf
xxpaper/LiberationSerif-Bold.ttf
xxpaper/LiberationSerif-BoldItalic.ttf
xxpaper/LiberationSerif-Italic.ttf
xxpaper/LiberationSerif-Regular.ttf
xxpaper/XXP_DEFAULT.xxp
xxpaper/XXP_assets_1.625x2.5.xxp
xxpaper/XXP_assets_41x63.xxp
xxpaper/XXP_assets_44x64.xxp
xxpaper/XXP_assets_44x67.xxp
xxpaper/XXP_catalogue.xxp
xxpaper/XXP_clips.xxp
xxpaper/XXP_colour.xxp
xxpaper/XXP_colour_hollasch.xxp
xxpaper/XXP_colour_resene.xxp
xxpaper/XXP_colour_scale.xxp
xxpaper/XXP_colour_wikipedia.xxp
xxpaper/XXP_colour_x11.xxp
xxpaper/XXP_colour_xxp.xxp
xxpaper/XXP_company.xxp
xxpaper/XXP_company_charter_objects.xxp
xxpaper/XXP_company_concession_objects.xxp
xxpaper/XXP_company_minor_charter_objects.xxp
xxpaper/XXP_company_narrow_charter_objects.xxp
xxpaper/XXP_company_share_objects.xxp
xxpaper/XXP_company_short_objects.xxp
xxpaper/XXP_company_wide_charter_objects.xxp
xxpaper/XXP_components.xxp
xxpaper/XXP_font_courier.xxp
xxpaper/XXP_font_helvetica.xxp
xxpaper/XXP_font_liberationsans.xxp
xxpaper/XXP_font_liberationserif.xxp
xxpaper/XXP_marker.xxp
xxpaper/XXP_market2d.xxp
xxpaper/XXP_private.xxp
xxpaper/XXP_swatch.xxp
xxpaper/XXP_tiles.xxp
xxpaper/XXP_token_objects.xxp
xxpaper/XXP_train.xxp
xxpaper/__init__.py
xxpaper/build.sh
xxpaper/cards.py
xxpaper/cmd_assets.py
xxpaper/cmd_cards.py
xxpaper/cmd_check.py
xxpaper/cmd_dump.py
xxpaper/cmd_lookup.py
xxpaper/cmds.py
xxpaper/config.py
xxpaper/config.py~
xxpaper/contents.py
xxpaper/document.py
xxpaper/document.py~
xxpaper/main.py
xxpaper/page.py
xxpaper/swatch_hollasch.xxp
xxpaper/swatch_resene.xxp
xxpaper/swatch_scale.xxp
xxpaper/swatch_wikipedia.xxp
xxpaper/swatch_x11.xxp
xxpaper/swatch_xxp.pdf
xxpaper/swatch_xxp.xxp
xxpaper/tile.py
xxpaper/xlate_frame.py
xxpaper-1.2.post6.dist-info/LICENSE
xxpaper-1.2.post6.dist-info/METADATA
xxpaper-1.2.post6.dist-info/WHEEL
xxpaper-1.2.post6.dist-info/entry_points.txt
xxpaper-1.2.post6.dist-info/RECORD
