Metadata-Version: 2.1
Name: xxpaper
Version: 1.2.post6
Summary: Tools for generating printable files for 18xx games.
Home-page: https://github.com/clearclaw/cfgstack
License: GPL-3.0-only
Author: J C Lawrence
Author-email: claw@kanga.nu
Requires-Python: >=3.8,<4.0
Classifier: License :: OSI Approved :: GNU General Public License v3 (GPLv3)
Classifier: Programming Language :: Python :: 3
Classifier: Programming Language :: Python :: 3.8
Classifier: Programming Language :: Python :: 3.9
Classifier: Programming Language :: Python :: 3.10
Classifier: Programming Language :: Python :: 3.11
Classifier: Programming Language :: Python :: 3.12
Requires-Dist: cfgstack (>=0.2.post2,<0.3)
Requires-Dist: clip-py (>=0.3.2,<0.4.0)
Requires-Dist: findfile-path (>=0.2.post3,<0.3)
Requires-Dist: logtool (>=0.4.post1,<0.5)
Requires-Dist: path (>=16.14.0,<17.0.0)
Requires-Dist: pyyaml (>=6.0.1,<7.0.0)
Requires-Dist: raven (>=6.10.0,<7.0.0)
Requires-Dist: reportlab (>=4.2.2,<5.0.0)
Requires-Dist: toml (>=0.10.2,<0.11.0)
Project-URL: Repository, https://github.com/clearclaw/cfgstack
